multikano/__init__.py
multikano/data_processing.py
multikano/model.py
multikano/utils.py
multikano-0.1.0.dist-info/LICENSE
multikano-0.1.0.dist-info/METADATA
multikano-0.1.0.dist-info/WHEEL
multikano-0.1.0.dist-info/top_level.txt
multikano-0.1.0.dist-info/RECORD
